incolumepy/__init__.py
incolumepy/sequencias/__init__.py
incolumepy/sequencias/version.txt
incolumepy.sequencias-1.0.dist-info/METADATA
incolumepy.sequencias-1.0.dist-info/RECORD
incolumepy.sequencias-1.0.dist-info/WHEEL
incolumepy.sequencias-1.0.dist-info/entry_points.txt
incolumepy.sequencias-1.0.dist-info/top_level.txt
